README.md
setup.py
number_recognition/__init__.py
number_recognition/main.py
number_recognition.egg-info/PKG-INFO
number_recognition.egg-info/SOURCES.txt
number_recognition.egg-info/dependency_links.txt
number_recognition.egg-info/requires.txt
number_recognition.egg-info/top_level.txt